dexpr/__init__.py
dexpr/calendar.py
dexpr/dgen.py
dexpr/exprclass.py
dexpr/magic.py
dexpr/tenor.py
dexpr-0.0.6.dist-info/LICENSE
dexpr-0.0.6.dist-info/METADATA
dexpr-0.0.6.dist-info/WHEEL
dexpr-0.0.6.dist-info/top_level.txt
dexpr-0.0.6.dist-info/RECORD
