Metadata-Version: 2.1
Name: dexpr
Version: 0.0.6
Summary: Libraries for capturing and using expressions in python
Author-email: wukrur <wukrur@github.com>
License: MIT
Keywords: expressions,date generators,extended dataclass
Classifier: Programming Language :: Python :: 3
Requires-Python: >=3.11
License-File: LICENSE
Requires-Dist: importlib-metadata ; python_version < "3.11"
